date_difference/__init__.py
date_difference/date_difference.py
date_difference-0.1.0.dist-info/METADATA
date_difference-0.1.0.dist-info/WHEEL
date_difference-0.1.0.dist-info/top_level.txt
date_difference-0.1.0.dist-info/RECORD
