Metadata-Version: 2.1
Name: date-difference
Version: 0.1.0
Summary: A Python library to calculate the difference between two dates.
Home-page: https://github.com/gihubuser72/date_difference.git
Author: devlopment-new10
Author-email: githubuser16@gmail.com
Classifier: Programming Language :: Python :: 3
Classifier: License :: OSI Approved :: MIT License
Classifier: Operating System :: OS Independent
Requires-Python: >=3.6
